cstructimpl/__init__.py
cstructimpl/c_annotations.py
cstructimpl/c_lib.py
cstructimpl/c_types.py
cstructimpl/util.py
cstructimpl-0.4.1.dist-info/licenses/LICENSE
cstructimpl-0.4.1.dist-info/METADATA
cstructimpl-0.4.1.dist-info/WHEEL
cstructimpl-0.4.1.dist-info/top_level.txt
cstructimpl-0.4.1.dist-info/RECORD
