Metadata-Version: 2.4
Name: cstructimpl
Version: 0.4.1
Summary: Python package to translate C struct to classes
Author: Brendon Mendicino
License-Expression: Apache-2.0
Project-URL: Repository, https://github.com/Brendon-Mendicino/cstructimpl
Project-URL: Issues, https://github.com/Brendon-Mendicino/cstructimpl/issues
Classifier: Development Status :: 4 - Beta
Classifier: Intended Audience :: Developers
Classifier: Topic :: Software Development :: Libraries
Classifier: Topic :: Software Development :: Code Generators
Classifier: Topic :: Utilities
Classifier: Programming Language :: Python
Classifier: Programming Language :: Python :: 3
Classifier: Programming Language :: Python :: 3.10
Classifier: Programming Language :: Python :: 3.11
Classifier: Programming Language :: Python :: 3.12
Classifier: Programming Language :: Python :: 3.13
Classifier: Typing :: Typed
Requires-Python: >=3.10
License-File: LICENSE
Provides-Extra: dev
Requires-Dist: pytest; extra == "dev"
Dynamic: license-file
